pacpoetry/.DS_Store
pacpoetry/__init__.py
pacpoetry/utils.py
package_poetry_20230104-0.1.1.dist-info/WHEEL
package_poetry_20230104-0.1.1.dist-info/METADATA
package_poetry_20230104-0.1.1.dist-info/RECORD
